exmachina/__init__.py
exmachina/core/depends_contoroller.py
exmachina/core/exception.py
exmachina/core/helper.py
exmachina/core/machina.py
exmachina/core/params.py
exmachina/core/params_function.py
exmachina/core/task.py
exmachina/lib/helper.py
exmachina/lib/retry.py
exmachina/lib/time_semaphore.py
exmachina-0.2.4.dist-info/WHEEL
exmachina-0.2.4.dist-info/METADATA
exmachina-0.2.4.dist-info/RECORD
