Metadata-Version: 2.1
Name: exmachina
Version: 0.2.4
Summary: botを作るためのフレームワークです
Home-page: https://github.com/agarichan/exmachina
License: MIT
Author: agarichan
Requires-Python: >=3.7,<4.0
Classifier: License :: OSI Approved :: MIT License
Classifier: Programming Language :: Python :: 3
Classifier: Programming Language :: Python :: 3.10
Classifier: Programming Language :: Python :: 3.7
Classifier: Programming Language :: Python :: 3.8
Classifier: Programming Language :: Python :: 3.9
Provides-Extra: rich
Requires-Dist: rich (>=10.1.0,<11.0.0); extra == "rich"
Requires-Dist: typing-extensions (>=3.10.0,<4.0.0)
Project-URL: Repository, https://github.com/agarichan/exmachina
